README.md
setup.cfg
setup.py
listenmoe/__init__.py
listenmoe/client.py
listenmoe/message.py
listenmoe.egg-info/PKG-INFO
listenmoe.egg-info/SOURCES.txt
listenmoe.egg-info/dependency_links.txt
listenmoe.egg-info/requires.txt
listenmoe.egg-info/top_level.txt