Metadata-Version: 1.1
Name: listenmoe
Version: 1.0.1
Summary: Unofficial python3 API wrapper to get information aboutthe listen.moe live stream using aiohttp
Home-page: https://github.com/Zenrac/listenmoe
Author: Zenrac
Author-email: zenrac@outlook.fr
License: UNKNOWN
Download-URL: https://github.com/Zenrac/listenmoe/archive/v1.0.1.tar.gz
Keywords: listenmoe
Platform: UNKNOWN
